Metadata-Version: 2.0
Name: Celeratas
Version: 1.3.1
Summary: The Latin Programming Language
Home-page: https://github.com/planto73/Celeratas
Author: Finn Mattis
Author-email: TopSecret@DontEmailMe.com
License: MIT
Platform: unix
Platform: linux
Platform: osx
Platform: win32
Classifier: Development Status :: 4 - Beta
Classifier: Intended Audience :: Developers
Classifier: License :: OSI Approved :: MIT License
Classifier: Natural Language :: English
Classifier: Natural Language :: Latin
Classifier: Operating System :: MacOS
Classifier: Operating System :: Microsoft :: Windows
Classifier: Operating System :: POSIX :: Linux
Classifier: Operating System :: Unix
Classifier: Programming Language :: Python :: 3
Classifier: Programming Language :: Python :: 3 :: Only
Classifier: Programming Language :: Python :: 3.6
Classifier: Programming Language :: Python :: 3.7
Classifier: Programming Language :: Python :: 3.8
Classifier: Programming Language :: Python :: 3.9
Classifier: Programming Language :: Python :: 3.10
Classifier: Programming Language :: Python :: 3.11
Classifier: Programming Language :: Python :: 3.12
Classifier: Topic :: Software Development :: Compilers
Requires-Python: >=3.6
Provides-Extra: autopep8 >
Provides-Extra: flake8 >
Provides-Extra: pytest >
Provides-Extra: pytest-cov >
Provides-Extra: tox >
Provides-Extra: build >
Provides-Extra: twine >
License-File: LICENSE
Requires-Dist: inquirer (>=2)
Requires-Dist: importlib-metadata (>=4)
Provides-Extra: autopep8 >
Requires-Dist: 1.0; extra == 'autopep8 >'
Provides-Extra: build >
Requires-Dist: 0.8; extra == 'build >'
Provides-Extra: flake8 >
Requires-Dist: 4.0; extra == 'flake8 >'
Provides-Extra: pytest >
Requires-Dist: 7.0; extra == 'pytest >'
Provides-Extra: pytest-cov >
Requires-Dist: 3.0; extra == 'pytest-cov >'
Provides-Extra: tox >
Requires-Dist: 3.0; extra == 'tox >'
Provides-Extra: twine >
Requires-Dist: 3.0; extra == 'twine >'
